{
  "schema_version": "1.1",
  "article_id": "IMG_TEST_MULTI_001",
  "title": "[테스트] 다양한 포맷 이미지 혼합 문서",
  "metadata": {
    "author": "테스터",
    "created_at": "2025-01-24T11:00:00+09:00",
    "updated_at": "2025-01-24T11:00:00+09:00",
    "department": "QA팀",
    "board_id": "BBNC100171030",
    "board_name": "테스트게시판",
    "board_path": ["BGF리테일게시판", "테스트게시판"],
    "board_depth": 2,
    "folder_id": "BFCC100171030",
    "expiry": "영구",
    "views": 3,
    "likes": 0,
    "comments": 0
  },
  "attachments": [],
  "attachment_count": 0,
  "total_attachment_size": 0,
  "contents": [
    {
      "type": "text",
      "value": "다양한 이미지 포맷이 하나의 문서에 혼합된 테스트입니다."
    },
    {
      "type": "text",
      "value": "1. PNG 이미지:"
    },
    {
      "type": "image",
      "url": "./test_img.png"
    },
    {
      "type": "text",
      "value": "2. JPG 이미지:"
    },
    {
      "type": "image",
      "url": "./test_img.jpg"
    },
    {
      "type": "text",
      "value": "3. GIF 이미지:"
    },
    {
      "type": "image",
      "url": "./test_img.gif"
    },
    {
      "type": "text",
      "value": "4. WebP 이미지:"
    },
    {
      "type": "image",
      "url": "./test_img.webp"
    },
    {
      "type": "text",
      "value": "5. AVIF 이미지:"
    },
    {
      "type": "image",
      "url": "./test_img.avif"
    },
    {
      "type": "text",
      "value": "모든 이미지가 정상적으로 삽입되었는지 확인합니다."
    }
  ],
  "content_html": ""
}
