{
  "schema_version": "1.1",
  "article_id": "BA000000000000000000008",
  "title": "[공지] 이미지 URL 테스트",
  "metadata": {
    "author": "테스터",
    "created_at": "2026-01-25T12:52:00+09:00",
    "updated_at": "2026-01-25T12:52:00+09:00",
    "department": "QA팀",
    "board_id": "BBNC100171030",
    "board_name": "공지사항",
    "board_path": ["BGF리테일게시판", "전사공지사항", "공지사항"],
    "board_depth": 3,
    "folder_id": "BFCC100171030",
    "expiry": "영구",
    "views": 5,
    "likes": 0,
    "comments": 0
  },
  "attachments": [],
  "attachment_count": 0,
  "total_attachment_size": 0,
  "contents": [
    {
      "type": "text",
      "value": "안녕하세요.\n\n아래는 외부 URL에서 가져온 이미지입니다."
    },
    {
      "type": "image",
      "url": "https://gw.hancom.com/ekp/service/file/fileView?module=board&fileUrl=/C100171030/board/image/2026/01/22&fileName=985d5330-d662-4443-bc4c-9341d7cde974.jpg"
    },
    {
      "type": "text",
      "value": "이미지가 정상적으로 삽입되었습니다.\n감사합니다."
    }
  ],
  "content_html": "<p>안녕하세요.</p>"
}
